{"Name of dataset": "moabb.datasets.MAMEM2 \u2014 moabb 0.4.5 documentation", "Dataset description": null, "References": "1MAMEM Steady State Visually Evoked Potential EEG Databasehttps://archive.physionet.org/physiobank/database/mssvepdb/2S. Nikolopoulos, 2016, DataAcquisitionDetails.pdfhttps://figshare.com/articles/dataset/MAMEM_EEG_SSVEP_Dataset_II_256_channels_11_subjects_5_frequencies_presented_simultaneously_/3153409?file=4911931  # noqa: E501", "Methods": "data_path(subject[,\u00a0path,\u00a0force_update,\u00a0\u2026])Get path to local copy of a subject data.download([subject_list,\u00a0path,\u00a0force_update,\u00a0\u2026])Download all data from the dataset.get_data([subjects])Return the data correspoonding to a list of subjects.", "Examples": null, "url": "http://moabb.neurotechx.com/docs/generated/moabb.datasets.MAMEM2.html#moabb.datasets.MAMEM2"}